pydavis/__init__.py
pydavis/data_logging.py
pydavis/db_manager.py
pydavis/utils.py
pydavis/web_scraping.py
pydavis-0.1.1.dist-info/METADATA
pydavis-0.1.1.dist-info/RECORD
pydavis-0.1.1.dist-info/WHEEL
pydavis-0.1.1.dist-info/top_level.txt
