Metadata-Version: 2.1
Name: pydavis
Version: 0.1.1
Summary: Tools to stream weather data from Davis weather stations.
Home-page: https://github.com/GSEL9/pydavis
Author: Severin Langberg
Author-email: langberg91@gmail.com
License: MIT
Keywords: data science,data analytics,web scraping,database,weather data,data collection,davis
Platform: UNKNOWN
Classifier: Development Status :: 3 - Alpha
Classifier: Environment :: Console
Classifier: Intended Audience :: Science/Research
Classifier: License :: OSI Approved :: MIT License
Classifier: Natural Language :: English
Classifier: Programming Language :: Python :: 3
Requires-Dist: sphinx
Requires-Dist: pymysql
Requires-Dist: beautifulsoup4
Requires-Dist: python-dateutil
